{"_type":"export","__export_format":4,"__export_date":"2023-10-04T20:01:03.834Z","__export_source":"insomnia.desktop.app:v2023.4.0","resources":[{"_id":"req_2ff82f0f182642f58c8302ff8553049b","parentId":"fld_7d20c95326004bafa12f7137ac18e452","modified":1695928893222,"created":1695922458800,"url":"http://localhost:8080/login","name":"Login","description":"","method":"POST","body":{"mimeType":"application/json","text":"{ \n\t\t\"id\":1,\n    \"nome\":\"Douglas\",\n    \"user_name\":\"Stouwlnia\",\n    \"senha\":\"123\"\n}"},"parameters":[],"headers":[{"name":"Content-Type","value":"application/json"},{"id":"pair_e0ec26906aac4446bcc3bc072b3b0089","name":"","value":"","description":""}],"authentication":{"type":"apikey","disabled":false,"key":"","value":"","addTo":"header"},"metaSortKey":-1695922458800,"isPrivate":false,"settingStoreCookies":true,"settingSendCookies":true,"settingDisableRenderRequestBody":false,"settingEncodeUrl":true,"settingRebuildPath":true,"settingFollowRedirects":"global","_type":"request"},{"_id":"fld_7d20c95326004bafa12f7137ac18e452","parentId":"wrk_ddabed0de4904067860ef34f04647498","modified":1695922454908,"created":1695922454908,"name":"Login","description":"","environment":{},"environmentPropertyOrder":null,"metaSortKey":-1695922454908,"_type":"request_group"},{"_id":"wrk_ddabed0de4904067860ef34f04647498","parentId":null,"modified":1696439727558,"created":1696439727558,"name":"My Collection","description":"","scope":"collection","_type":"workspace"},{"_id":"req_153d1351d15e4e748d84a602bad24398","parentId":"fld_7d20c95326004bafa12f7137ac18e452","modified":1695928885490,"created":1695922744286,"url":"http://localhost:8080/usuario","name":"Usuario","description":"","method":"GET","body":{},"parameters":[],"headers":[],"authentication":{},"metaSortKey":-1695922458750,"isPrivate":false,"settingStoreCookies":true,"settingSendCookies":true,"settingDisableRenderRequestBody":false,"settingEncodeUrl":true,"settingRebuildPath":true,"settingFollowRedirects":"global","_type":"request"},{"_id":"req_35c5efa74be9420e952841c993ab6c41","parentId":"fld_35bbe83588d94613ae1253cce8e1b72d","modified":1695412184717,"created":1695410645190,"url":"http://localhost:8080/soma","name":"Soma","description":"","method":"GET","body":{},"parameters":[],"headers":[],"authentication":{},"metaSortKey":-1695410645127.5,"isPrivate":false,"settingStoreCookies":true,"settingSendCookies":true,"settingDisableRenderRequestBody":false,"settingEncodeUrl":true,"settingRebuildPath":true,"settingFollowRedirects":"global","_type":"request"},{"_id":"fld_35bbe83588d94613ae1253cce8e1b72d","parentId":"wrk_ddabed0de4904067860ef34f04647498","modified":1695410642626,"created":1695410642626,"name":"Soma","description":"","environment":{},"environmentPropertyOrder":null,"metaSortKey":-1695410642626,"_type":"request_group"},{"_id":"req_a0b4247c66074123b6a126d2906fe648","parentId":"fld_35bbe83588d94613ae1253cce8e1b72d","modified":1695921326815,"created":1695410672053,"url":"http://localhost:8080/soma/parametros","name":"Soma Parametros","description":"","method":"POST","body":{"mimeType":"application/json","text":"{\n\t\"valor1\":10,\n\t\"valor2\":20\n}"},"parameters":[],"headers":[{"name":"Content-Type","value":"application/json"}],"authentication":{},"metaSortKey":-1695410645077.5,"isPrivate":false,"settingStoreCookies":true,"settingSendCookies":true,"settingDisableRenderRequestBody":false,"settingEncodeUrl":true,"settingRebuildPath":true,"settingFollowRedirects":"global","_type":"request"},{"_id":"req_8f2437d9cc1d498f82f129df799a4388","parentId":"fld_a6615227ee044a92a7e33e09db7b8773","modified":1695406640653,"created":1695406608492,"url":"http://localhost:8080/professores","name":"Professores","description":"","method":"GET","body":{},"parameters":[],"headers":[],"authentication":{},"metaSortKey":-1695406608492,"isPrivate":false,"settingStoreCookies":true,"settingSendCookies":true,"settingDisableRenderRequestBody":false,"settingEncodeUrl":true,"settingRebuildPath":true,"settingFollowRedirects":"global","_type":"request"},{"_id":"fld_a6615227ee044a92a7e33e09db7b8773","parentId":"wrk_ddabed0de4904067860ef34f04647498","modified":1695406606208,"created":1695406606208,"name":"Professores","description":"","environment":{},"environmentPropertyOrder":null,"metaSortKey":-1695406606208,"_type":"request_group"},{"_id":"req_8ba617695c8c46ce9c98e333e13fe36c","parentId":"fld_a6615227ee044a92a7e33e09db7b8773","modified":1695406694449,"created":1695406643386,"url":"http://localhost:8080/professores/material","name":"Professores - Material","description":"","method":"GET","body":{},"parameters":[],"headers":[],"authentication":{},"metaSortKey":-1695406608442,"isPrivate":false,"settingStoreCookies":true,"settingSendCookies":true,"settingDisableRenderRequestBody":false,"settingEncodeUrl":true,"settingRebuildPath":true,"settingFollowRedirects":"global","_type":"request"},{"_id":"req_8423dd3367514d38a83d01ce62268a26","parentId":"fld_a6615227ee044a92a7e33e09db7b8773","modified":1695406725599,"created":1695406707076,"url":"http://localhost:8080/professores/atividades","name":"Professores - Atividades","description":"","method":"GET","body":{},"parameters":[],"headers":[],"authentication":{},"metaSortKey":-1695406608392,"isPrivate":false,"settingStoreCookies":true,"settingSendCookies":true,"settingDisableRenderRequestBody":false,"settingEncodeUrl":true,"settingRebuildPath":true,"settingFollowRedirects":"global","_type":"request"},{"_id":"req_d715995309014950b8576fd8341fb124","parentId":"fld_a6615227ee044a92a7e33e09db7b8773","modified":1695406749259,"created":1695406729886,"url":"http://localhost:8080/professores/notas","name":"Professores - Notas","description":"","method":"GET","body":{},"parameters":[],"headers":[],"authentication":{},"metaSortKey":-1695406608342,"isPrivate":false,"settingStoreCookies":true,"settingSendCookies":true,"settingDisableRenderRequestBody":false,"settingEncodeUrl":true,"settingRebuildPath":true,"settingFollowRedirects":"global","_type":"request"},{"_id":"req_75d5d93af6a54148ae58df9dccbc6eb3","parentId":"fld_ab954421f4534964970920c4a9e7ac69","modified":1695405739265,"created":1695404227852,"url":"http://localhost:8080/alunos","name":"Alunos","description":"","method":"GET","body":{},"parameters":[],"headers":[],"authentication":{},"metaSortKey":-1695404767645,"isPrivate":false,"settingStoreCookies":true,"settingSendCookies":true,"settingDisableRenderRequestBody":false,"settingEncodeUrl":true,"settingRebuildPath":true,"settingFollowRedirects":"global","_type":"request"},{"_id":"fld_ab954421f4534964970920c4a9e7ac69","parentId":"wrk_ddabed0de4904067860ef34f04647498","modified":1695405735195,"created":1695405735195,"name":"Alunos","description":"","environment":{},"environmentPropertyOrder":null,"metaSortKey":-1695405735195,"_type":"request_group"},{"_id":"req_e6427ec71eee4f82846d7769ba0ea340","parentId":"fld_ab954421f4534964970920c4a9e7ac69","modified":1695406766285,"created":1695404767695,"url":"http://localhost:8080/alunos","name":"Alunos - Notas","description":"","method":"GET","body":{},"parameters":[],"headers":[],"authentication":{},"metaSortKey":-1695404767595,"isPrivate":false,"settingStoreCookies":true,"settingSendCookies":true,"settingDisableRenderRequestBody":false,"settingEncodeUrl":true,"settingRebuildPath":true,"settingFollowRedirects":"global","_type":"request"},{"_id":"req_85279744f42242ebabf2540190eb4ca0","parentId":"fld_ab954421f4534964970920c4a9e7ac69","modified":1695406848180,"created":1695406768490,"url":"http://localhost:8080/alunos/atividades","name":"Alunos - Atividades","description":"","method":"GET","body":{},"parameters":[],"headers":[],"authentication":{},"metaSortKey":-1695404767545,"isPrivate":false,"settingStoreCookies":true,"settingSendCookies":true,"settingDisableRenderRequestBody":false,"settingEncodeUrl":true,"settingRebuildPath":true,"settingFollowRedirects":"global","_type":"request"},{"_id":"req_a0564ac3f7074e2ebef14c697988bb68","parentId":"fld_ab954421f4534964970920c4a9e7ac69","modified":1695406896603,"created":1695406877818,"url":"http://localhost:8080/alunos/livros","name":"Alunos - Livros","description":"","method":"GET","body":{},"parameters":[],"headers":[],"authentication":{},"metaSortKey":-1695404767520,"isPrivate":false,"settingStoreCookies":true,"settingSendCookies":true,"settingDisableRenderRequestBody":false,"settingEncodeUrl":true,"settingRebuildPath":true,"settingFollowRedirects":"global","_type":"request"},{"_id":"req_b9b702e117e2488b80ed3b8ca5dcc88d","parentId":"fld_ab954421f4534964970920c4a9e7ac69","modified":1695406872804,"created":1695406850765,"url":"http://localhost:8080/alunos/perfil","name":"Alunos - Perfil","description":"","method":"GET","body":{},"parameters":[],"headers":[],"authentication":{},"metaSortKey":-1695404767495,"isPrivate":false,"settingStoreCookies":true,"settingSendCookies":true,"settingDisableRenderRequestBody":false,"settingEncodeUrl":true,"settingRebuildPath":true,"settingFollowRedirects":"global","_type":"request"},{"_id":"req_d59545ea25be44eaad3639c8e3c01ae6","parentId":"fld_ab954421f4534964970920c4a9e7ac69","modified":1696449210629,"created":1696446601756,"url":"http://localhost:8080/alunos/3","name":"Busca por Id","description":"","method":"GET","body":{},"parameters":[],"headers":[],"authentication":{},"metaSortKey":-1695404767445,"isPrivate":false,"settingStoreCookies":true,"settingSendCookies":true,"settingDisableRenderRequestBody":false,"settingEncodeUrl":true,"settingRebuildPath":true,"settingFollowRedirects":"global","_type":"request"},{"_id":"env_02e6177a7ed94ebc8750ca409280280a","parentId":"wrk_ddabed0de4904067860ef34f04647498","modified":1695920476394,"created":1695920476394,"name":"Base Environment","data":{},"dataPropertyOrder":null,"color":null,"isPrivate":false,"metaSortKey":1695920476394,"_type":"environment"},{"_id":"jar_6d891d7b65934469956b8a11b38d63ac","parentId":"wrk_ddabed0de4904067860ef34f04647498","modified":1695920476397,"created":1695920476397,"name":"Default Jar","cookies":[],"_type":"cookie_jar"}]}